symnet_cp/__init__.py
symnet_cp/controller.py
symnet_cp/device.py
symnet_cp/protocol.py
symnet_cp-0.6.0.dist-info/LICENSE
symnet_cp-0.6.0.dist-info/METADATA
symnet_cp-0.6.0.dist-info/WHEEL
symnet_cp-0.6.0.dist-info/RECORD
